{
  "$schema": "https://json-schema.org/draft/2020-12/schema",
  "title": "WorkspaceProvisioningStarted",
  "description": "CloudEvent: WorkspaceProvisioningStarted",
  "type": "object",
  "source": "server",
  "required": [
    "specversion",
    "id",
    "source",
    "type",
    "datacontenttype",
    "time",
    "traceparent",
    "tenantId"
  ],
  "properties": {
    "specversion": {
      "type": "string",
      "const": "1.0"
    },
    "id": {
      "type": "string",
      "description": "UUID \u2014 unique per event instance"
    },
    "source": {
      "type": "string",
      "const": "xiigen/onboarding-delivery"
    },
    "type": {
      "type": "string",
      "const": "xiigen.user-registration.workspaceprovisioningstarted.v1"
    },
    "datacontenttype": {
      "type": "string",
      "const": "application/json"
    },
    "time": {
      "type": "string",
      "format": "date-time"
    },
    "traceparent": {
      "type": "string"
    },
    "tenantId": {
      "type": "string",
      "description": "Tenant scope \u2014 required on every event (DNA-5)"
    },
    "data": {
      "type": "object",
      "description": "Event data \u2014 no PII (CF-8). userId as reference only.",
      "required": [
        "userId",
        "workspaceId",
        "correlationId"
      ],
      "properties": {
        "userId": {
          "type": "string"
        },
        "workspaceId": {
          "type": "string"
        },
        "correlationId": {
          "type": "string"
        }
      }
    }
  },
  "additionalProperties": false,
  "seededAt": "2026-03-24T22:09:46.555074+00:00",
  "flowId": "FLOW-01"
}