{
  "_index": "xiigen-arbiters",
  "_id": "FLOW-32-secret_ref_indirection",
  "checkId": "secret_ref_indirection",
  "flowId": "FLOW-32",
  "bfaRule": "CF-726",
  "severity": "BUILD_FAILURE",
  "description": "T523 binding documents must store only secret reference IDs. Literal secret values in generated code are a security violation.",
  "taskTypeIds": ["T523"],
  "scanFor": {
    "banned": ["password =", "apiKey =", "token =", "secret =", "privateKey ="],
    "anyPresent": "FAIL"
  },
  "required": ["secretRef", "vaultRef", "ISecretsService"],
  "onFailure": "BUILD_FAILURE",
  "ddRef": "DD-327",
  "failureMessage": "CF-726/DD-327: Literal secret value in T523 binding document. Use secretRef/vaultRef via ISecretsService.",
  "active": true
}
