{
    "flowId":  "FLOW-15",
    "flowSlug":  "saas-multi-tenancy",
    "phase":  "phase5cTenantCInstalls",
    "status":  "completed",
    "generatedAt":  "2026-05-06T15:49:47.3206386+03:00",
    "tenant":  {
                   "tenantId":  "tessera-collective",
                   "tenantName":  "Tessera Collective"
               },
    "sourceTenant":  {
                         "tenantId":  "northwind",
                         "package":  "@xiigen-fork/northwind-controlled-saas-multi-tenancy",
                         "version":  "1.0.2",
                         "repo":  "lubochka/northwind--northwind-controlled-saas-multi-tenancy"
                     },
    "install":  {
                    "type":  "marketplace-api-fork-from-tenant-b-published-package",
                    "request":  {
                                    "endpoint":  "POST /api/marketplace/packages/saas-multi-tenancy/fork",
                                    "tenantId":  "tessera-collective",
                                    "sourceRepoFullName":  "lubochka/northwind--northwind-controlled-saas-multi-tenancy",
                                    "repoNameOverride":  "tessera-collective--northwind-controlled-saas-multi-tenancy",
                                    "initialVersion":  "1.0.2"
                                },
                    "repo":  "lubochka/tessera-collective--northwind-controlled-saas-multi-tenancy",
                    "url":  "https://github.com/lubochka/tessera-collective--northwind-controlled-saas-multi-tenancy",
                    "defaultBranch":  "main",
                    "visibilityAfterEvidence":  "PRIVATE",
                    "installedFromRepoFullName":  "lubochka/northwind--northwind-controlled-saas-multi-tenancy",
                    "packageName":  "@xiigen-fork/northwind-controlled-saas-multi-tenancy",
                    "packageVersion":  "1.0.2",
                    "moduleName":  "northwind-controlled-saas-multi-tenancy",
                    "tenantConfigTenantId":  "tessera-collective",
                    "adaptationHistoryEntries":  2,
                    "adaptationHistoryPublishers":  [
                                                        "acme-corp",
                                                        "northwind"
                                                    ]
                },
    "tenantRepository":  {
                             "repo":  "lubochka/tessera-collective--northwind-controlled-saas-multi-tenancy",
                             "url":  "https://github.com/lubochka/tessera-collective--northwind-controlled-saas-multi-tenancy",
                             "defaultBranch":  "main",
                             "visibilityAfterEvidence":  "PRIVATE",
                             "privateAfterEvidenceCapture":  true,
                             "initialCommitSha":  "8bd5f26d7625fb1181ee235f48bff132ae5db8c8",
                             "repairCommit":  "57f27a8112dbc7df6cc8c3a980101de1d9a201f5",
                             "repairCommitMessage":  "Repair Tessera install proof for Northwind SaaS tenancy",
                             "cleanClonePath":  "C:/Projects/xiigen-fork-clones/tessera-collective--northwind-controlled-saas-multi-tenancy-phase5c-20260506-153000",
                             "cleanCloneStatus":  "clean",
                             "filesChangedInTenantRepo":  [
                                                              "__tests__/saas-multi-tenancy-package.spec.ts"
                                                          ],
                             "tenantCloneVerification":  [
                                                             {
                                                                 "command":  "npm install --no-audit --no-fund",
                                                                 "result":  "passed"
                                                             },
                                                             {
                                                                 "command":  "npx tsc --noEmit --pretty false",
                                                                 "result":  "passed"
                                                             },
                                                             {
                                                                 "command":  "npx jest --colors=false --forceExit",
                                                                 "result":  "passed",
                                                                 "suites":  1,
                                                                 "tests":  3
                                                             }
                                                         ]
                         },
    "githubActions":  {
                          "initialRun":  {
                                             "runId":  25435227554,
                                             "url":  "https://github.com/lubochka/tessera-collective--northwind-controlled-saas-multi-tenancy/actions/runs/25435227554",
                                             "headSha":  "8bd5f26d7625fb1181ee235f48bff132ae5db8c8",
                                             "status":  "completed",
                                             "conclusion":  "failure",
                                             "failureReason":  "Inherited proof expected Northwind tenant identity after the fork engine correctly rewrote tenant.config.json to tessera-collective."
                                         },
                          "repairRun":  {
                                            "workflowName":  "XIIGen Flow CI — saas-multi-tenancy",
                                            "runId":  25435671454,
                                            "jobId":  74612874741,
                                            "url":  "https://github.com/lubochka/tessera-collective--northwind-controlled-saas-multi-tenancy/actions/runs/25435671454",
                                            "event":  "push",
                                            "status":  "completed",
                                            "conclusion":  "success",
                                            "headSha":  "57f27a8112dbc7df6cc8c3a980101de1d9a201f5",
                                            "createdAt":  "2026-05-06T12:37:43Z",
                                            "updatedAt":  "2026-05-06T12:38:33Z",
                                            "successfulSteps":  [
                                                                    "Install",
                                                                    "TypeScript check",
                                                                    "Test",
                                                                    "Provenance"
                                                                ]
                                        }
                      },
    "localRegistry":  {
                          "registryUrl":  "http://localhost:4873",
                          "viewCommand":  "npm view @xiigen-fork/northwind-controlled-saas-multi-tenancy@1.0.2 --registry http://localhost:4873 --json",
                          "packageName":  "@xiigen-fork/northwind-controlled-saas-multi-tenancy",
                          "npmViewVersion":  "1.0.2",
                          "distTags":  {
                                           "latest":  "1.0.2"
                                       },
                          "tarball":  "http://localhost:4873/@xiigen-fork/northwind-controlled-saas-multi-tenancy/-/northwind-controlled-saas-multi-tenancy-1.0.2.tgz",
                          "shasum":  "202044bbf9a4ccfeb4e7727c60fd09a0f5586ab0",
                          "gitHead":  "d6061af16b68a4fa0970bd0090b4b4b5dba0260b",
                          "apiEvidence":  "docs/e2e-snapshots/marketplace/saas-multi-tenancy-northwind-v1.0.2-registry-api-evidence-phase5c.json",
                          "verified":  true
                      },
    "visualEvidence":  {
                           "cascadeScreenshots":  {
                                                      "directory":  "docs/e2e-snapshots/saas-multi-tenancy/tenant-c-installed-from-b",
                                                      "count":  18,
                                                      "zeroByteFiles":  0,
                                                      "projects":  [
                                                                       "chromium-desktop",
                                                                       "chromium-mobile",
                                                                       "chromium-tablet"
                                                                   ]
                                                  },
                           "repoHomepageScreenshot":  {
                                                          "path":  "docs/e2e-snapshots/repo-evidence/flow-15/tessera-collective--northwind-controlled-saas-multi-tenancy-tenant-c-installed-from-b-github-listing.png",
                                                          "bytes":  127296,
                                                          "width":  0,
                                                          "height":  133
                                                      },
                           "actionsSuccessScreenshot":  {
                                                            "path":  "docs/e2e-snapshots/repo-evidence/flow-15/tessera-collective--northwind-controlled-saas-multi-tenancy-tenant-c-installed-from-b-actions-success.png",
                                                            "bytes":  77210,
                                                            "width":  0,
                                                            "height":  104
                                                        },
                           "registryScreenshot":  {
                                                      "path":  "docs/e2e-snapshots/marketplace/saas-multi-tenancy-northwind-v1.0.2-registry-listing-phase5c.png",
                                                      "bytes":  46454,
                                                      "width":  0,
                                                      "height":  208
                                                  }
                       },
    "mainRepoChangesForCascadeEvidence":  {
                                              "files":  [
                                                            "client/e2e/saas-multi-tenancy-tenant-c-installed.spec.ts"
                                                        ],
                                              "purpose":  "Render and verify FLOW-15 Tenant C installed-from-B cascade-point visual evidence under docs/e2e-snapshots/saas-multi-tenancy/tenant-c-installed-from-b."
                                          },
    "phaseCloseVerification":  {
                                   "clientTypeScript":  {
                                                            "command":  "client: npx tsc --noEmit --pretty false",
                                                            "result":  "passed"
                                                        },
                                   "tenantCInstalledPlaywright":  {
                                                                      "command":  "client: VITE_PORT=5174 npx playwright test e2e/saas-multi-tenancy-tenant-c-installed.spec.ts --reporter=list",
                                                                      "result":  "passed",
                                                                      "tests":  18
                                                                  },
                                   "serverTypeScript":  {
                                                            "command":  "server: npx tsc --noEmit -p tsconfig.json --pretty false",
                                                            "result":  "passed"
                                                        },
                                   "serverJest":  {
                                                      "command":  "server: npx jest --testPathPatterns=saas-multi-tenancy --runInBand --colors=false",
                                                      "result":  "passed",
                                                      "suites":  8,
                                                      "tests":  111
                                                  },
                                   "flowScans":  {
                                                     "throwNew":  0,
                                                     "servicesMissingMicroserviceBase":  0,
                                                     "clsImports":  0,
                                                     "directTenantContextImports":  0,
                                                     "anyTypes":  0,
                                                     "secretPatternHits":  0
                                                 }
                               },
    "secretHandling":  {
                           "tokensPrinted":  false,
                           "tokenValuesWrittenToEvidence":  false,
                           "tokenValuesCommitted":  false,
                           "envFilesCommitted":  false,
                           "repoScreenshotVisibilityWindowRestoredToPrivate":  true,
                           "registryTokenPrinted":  false
                       },
    "phaseGate":  {
                      "tenantCInstalledFromTenantB":  true,
                      "tenantCCommittedToRealRepo":  true,
                      "realGitHubActionsGreen":  true,
                      "localRegistryReturnsTenantBAdaptedVersion":  true,
                      "githubRepoScreenshotsPresent":  true,
                      "registryScreenshotPresent":  true,
                      "cascadeScreenshotsPresent":  true,
                      "phaseCloseScansClean":  true,
                      "readyForTenantCAdaptation":  true
                  },
    "verdict":  "PASS"
}
